poetry_group_override/__init__.py
poetry_group_override/plugin.py
poetry_group_override-0.1.1.dist-info/entry_points.txt
poetry_group_override-0.1.1.dist-info/METADATA
poetry_group_override-0.1.1.dist-info/WHEEL
poetry_group_override-0.1.1.dist-info/RECORD
