Metadata-Version: 2.1
Name: poetry-group-override
Version: 0.1.1
Summary: 
Home-page: https://github.com/Ewen-Zippedscript/poetry-group-override
Author: Ewen-Zippedscript
Author-email: ewen@zippedscript.com
Requires-Python: >=3.7,<4.0
Classifier: Programming Language :: Python :: 3
Classifier: Programming Language :: Python :: 3.7
Classifier: Programming Language :: Python :: 3.8
Classifier: Programming Language :: Python :: 3.9
Classifier: Programming Language :: Python :: 3.10
Classifier: Programming Language :: Python :: 3.11
Classifier: Programming Language :: Python :: 3.12
Requires-Dist: poetry (>=1.2.0,<2.0.0)
Project-URL: Repository, https://github.com/Ewen-Zippedscript/poetry-group-override
